{
  "main": {
    "id": "283032c32a11c6e8",
    "type": "split",
    "children": [
      {
        "id": "fcfd4052508897bd",
        "type": "tabs",
        "children": [
          {
            "id": "1a4cdee3469b7cf0",
            "type": "leaf",
            "state": {
              "type": "markdown",
              "state": {
                "file": "PIVOTING, TUNNELING, AND PORT FORWARDING 73f7c5471d9b4cefb900fbfb23e82310.md",
                "mode": "source",
                "source": false
              }
            }
          }
        ]
      }
    ],
    "direction": "vertical"
  },
  "left": {
    "id": "f8d7e3c836a0307c",
    "type": "split",
    "children": [
      {
        "id": "9fd9603fd67dea68",
        "type": "tabs",
        "children": [
          {
            "id": "efef18d6d003dd01",
            "type": "leaf",
            "state": {
              "type": "file-explorer",
              "state": {
                "sortOrder": "alphabetical"
              }
            }
          },
          {
            "id": "9da974db47e82fcf",
            "type": "leaf",
            "state": {
              "type": "search",
              "state": {
                "query": "",
                "matchingCase": false,
                "explainSearch": false,
                "collapseAll": false,
                "extraContext": false,
                "sortOrder": "alphabetical"
              }
            }
          },
          {
            "id": "388bcac8c1c9ffd2",
            "type": "leaf",
            "state": {
              "type": "bookmarks",
              "state": {}
            }
          }
        ]
      }
    ],
    "direction": "horizontal",
    "width": 359.5
  },
  "right": {
    "id": "3657e4e73b625eb9",
    "type": "split",
    "children": [
      {
        "id": "40729bf194c74486",
        "type": "tabs",
        "children": [
          {
            "id": "0546d994eb3cded1",
            "type": "leaf",
            "state": {
              "type": "backlink",
              "state": {
                "file": "PIVOTING, TUNNELING, AND PORT FORWARDING 73f7c5471d9b4cefb900fbfb23e82310.md",
                "collapseAll": false,
                "extraContext": false,
                "sortOrder": "alphabetical",
                "showSearch": false,
                "searchQuery": "",
                "backlinkCollapsed": false,
                "unlinkedCollapsed": true
              }
            }
          },
          {
            "id": "c78ce73c66574f37",
            "type": "leaf",
            "state": {
              "type": "outgoing-link",
              "state": {
                "file": "PIVOTING, TUNNELING, AND PORT FORWARDING 73f7c5471d9b4cefb900fbfb23e82310.md",
                "linksCollapsed": false,
                "unlinkedCollapsed": true
              }
            }
          },
          {
            "id": "67290dea33e1b232",
            "type": "leaf",
            "state": {
              "type": "tag",
              "state": {
                "sortOrder": "frequency",
                "useHierarchy": true
              }
            }
          },
          {
            "id": "4d70e9a88b9e1927",
            "type": "leaf",
            "state": {
              "type": "outline",
              "state": {
                "file": "PIVOTING, TUNNELING, AND PORT FORWARDING 73f7c5471d9b4cefb900fbfb23e82310.md"
              }
            }
          }
        ]
      }
    ],
    "direction": "horizontal",
    "width": 300,
    "collapsed": true
  },
  "left-ribbon": {
    "hiddenItems": {
      "switcher:Open quick switcher": false,
      "graph:Open graph view": false,
      "canvas:Create new canvas": false,
      "daily-notes:Open today's daily note": false,
      "templates:Insert template": false,
      "command-palette:Open command palette": false
    }
  },
  "active": "1a4cdee3469b7cf0",
  "lastOpenFiles": [
    ".git/index.lock",
    ".gitbook/assets/analyzingTheTraffic 1.gif",
    "PIVOTING, TUNNELING, AND PORT FORWARDING 73f7c5471d9b4cefb900fbfb23e82310.md",
    "pivoting, tunneling and port forwarding.md",
    ".gitbook/assets/Untitled 6.png",
    ".gitbook/assets/Untitled 5 1.png",
    ".gitbook/assets/Untitled 4 1.png",
    ".gitbook/assets/Untitled 3 1.png",
    ".gitbook/assets/Untitled 2 1.png",
    ".gitbook/assets/Untitled 1 2.png",
    ".gitbook/assets/PivotingandTunnelingVisualized 1.gif",
    "PIVOTING, TUNNELING, AND PORT FORWARDING 73f7c5471d9b4cefb900fbfb23e82310",
    ".git/objects/7f/4398a7046f8a05e4dce239ad510ea06354343f",
    ".git/objects/7f",
    ".git/objects/1e/0d2de7825d876d60b48d65bbaadbbe3f2a7863",
    ".git/objects/1e",
    ".git/objects/7e/11a0584437d7e00aa478f21cf267fddb2e63b8",
    ".git/objects/7e",
    ".git/objects/50/53ee67a5208632f84c20afe1cedb7ef9b15d80",
    ".git/objects/50",
    ".gitbook/assets/Untitled.png",
    ".gitbook/assets/Untitled 2.png",
    "shells-and-payloads.md",
    "penetration-testing-process.md",
    "pivoting-tunneling-and-port-forwarding.md",
    "pivoting-tunneling-and-port-forwarding-73f7c5471d9b4cefb900fbfb23e82310.md"
  ]
}